notiondl/__init__.py
notiondl/__main__.py
notiondl/cli.py
notiondl/main.py
notiondl/utils.py
notiondl-0.2.1.dist-info/LICENSE
notiondl-0.2.1.dist-info/METADATA
notiondl-0.2.1.dist-info/WHEEL
notiondl-0.2.1.dist-info/entry_points.txt
notiondl-0.2.1.dist-info/RECORD
