Metadata-Version: 2.1
Name: notiondl
Version: 0.2.1
Summary: Export and download Notion pages asynchronously
Home-page: https://github.com/0x7d4/notiondl
License: MIT
Author: Mohammad Momeni
Author-email: lo3me@pm.me
Requires-Python: >=3.7,<4.0
Classifier: License :: OSI Approved :: MIT License
Classifier: Programming Language :: Python :: 3
Classifier: Programming Language :: Python :: 3.7
Classifier: Programming Language :: Python :: 3.8
Classifier: Programming Language :: Python :: 3.9
Classifier: Programming Language :: Python :: 3.10
Classifier: Programming Language :: Python :: 3.11
Requires-Dist: requests (>=2.31.0,<3.0.0)
Requires-Dist: tqdm (>=4.66.1,<5.0.0)
Requires-Dist: urllib3 (==1.26.15)
Project-URL: Bug Tracker, https://github.com/0x7d4/notiondl/issues
Project-URL: Repository, https://github.com/0x7d4/notiondl
